ddddocr/__init__.py
ddddocr/_charset.py
ddddocr/py.typed
ddddocr_basic-1.5.6.post1.dist-info/LICENSE
ddddocr_basic-1.5.6.post1.dist-info/METADATA
ddddocr_basic-1.5.6.post1.dist-info/WHEEL
ddddocr_basic-1.5.6.post1.dist-info/top_level.txt
ddddocr_basic-1.5.6.post1.dist-info/RECORD
